piwavelet/__init__.py
piwavelet/motherWavelets.py
piwavelet/piwavelet.py
piwavelet/plotWavelet.py
piwavelet/smooth.py
piwavelet/wcoherence.py
piwavelet/wtc/Readme.txt
piwavelet/wtc/__init__.py
piwavelet/wtc/anglemean.m
piwavelet/wtc/ar1.m
piwavelet/wtc/ar1noise.m
piwavelet/wtc/ar1nv.m
piwavelet/wtc/ar1spectrum.m
piwavelet/wtc/arrow.m
piwavelet/wtc/boxpdf.m
piwavelet/wtc/chisquare_inv.m
piwavelet/wtc/chisquare_solve.m
piwavelet/wtc/colorbarf.m
piwavelet/wtc/formatts.m
piwavelet/wtc/jao.txt
piwavelet/wtc/jbaltic.txt
piwavelet/wtc/loadbnm.m
piwavelet/wtc/normalizepdf.m
piwavelet/wtc/parseArgs.m
piwavelet/wtc/phaseplot.m
piwavelet/wtc/rednoise.m
piwavelet/wtc/savebnm.m
piwavelet/wtc/smoothwavelet.m
piwavelet/wtc/versionhistory.txt
piwavelet/wtc/wave_bases.m
piwavelet/wtc/wave_signif.m
piwavelet/wtc/wavelet.m
piwavelet/wtc/wavetest.m
piwavelet/wtc/wt.m
piwavelet/wtc/wtc.m
piwavelet/wtc/wtcdemo.m
piwavelet/wtc/wtcsignif.m
piwavelet/wtc/xwt.m
piwavelet/wtc/example/__init__.py
piwavelet/wtc/example/faq.html
piwavelet/wtc/example/faq.png
piwavelet/wtc/example/faq_01.png
piwavelet/wtc/example/faq_02.png
piwavelet/wtc/example/faq_03.png
piwavelet/wtc/example/faq_04.png
piwavelet/wtc/example/faq_05.png
piwavelet/wtc/example/faq_06.png
piwavelet/wtc/example/wtcdemo.html
piwavelet/wtc/example/wtcdemo.png
piwavelet/wtc/example/wtcdemo_01.png
piwavelet/wtc/example/wtcdemo_02.png
piwavelet/wtc/example/wtcdemo_03.png
piwavelet-1.0.3.data/data/mfiles/wtc/Readme.txt
piwavelet-1.0.3.data/data/mfiles/wtc/__init__.py
piwavelet-1.0.3.data/data/mfiles/wtc/anglemean.m
piwavelet-1.0.3.data/data/mfiles/wtc/ar1.m
piwavelet-1.0.3.data/data/mfiles/wtc/ar1noise.m
piwavelet-1.0.3.data/data/mfiles/wtc/ar1nv.m
piwavelet-1.0.3.data/data/mfiles/wtc/ar1spectrum.m
piwavelet-1.0.3.data/data/mfiles/wtc/arrow.m
piwavelet-1.0.3.data/data/mfiles/wtc/boxpdf.m
piwavelet-1.0.3.data/data/mfiles/wtc/chisquare_inv.m
piwavelet-1.0.3.data/data/mfiles/wtc/chisquare_solve.m
piwavelet-1.0.3.dist-info/METADATA
piwavelet-1.0.3.dist-info/WHEEL
piwavelet-1.0.3.dist-info/top_level.txt
piwavelet-1.0.3.dist-info/RECORD
