Metadata-Version: 2.1
Name: piwavelet
Version: 1.0.3
Summary: Tools For Wavelet Analises in Python
Home-page: https://github.com/duducosmos/piwavelet
Author: Eduardo dos Santos Pereira
Author-email: pereira.somoza@gmail.com
License: Apache License 2.0
Keywords: wavelet signal analises
Platform: UNKNOWN
Requires-Dist: matplotlib (>=1.1.1)
Requires-Dist: numpy (>=1.6.2)
Requires-Dist: oct2py (>=2.0.0)
Requires-Dist: scipy (>=0.10.1)
